update_rpm/__init__.py
update_rpm/update_rpm.py
update_rpm-0.1.2.dist-info/LICENSE
update_rpm-0.1.2.dist-info/METADATA
update_rpm-0.1.2.dist-info/WHEEL
update_rpm-0.1.2.dist-info/entry_points.txt
update_rpm-0.1.2.dist-info/RECORD
